lanyocr/__init__.py
lanyocr/lanyocr_utils.py
lanyocr/angle_classifier/__init__.py
lanyocr/angle_classifier/paddleocr_angle_classifier_v2.py
lanyocr/benchmarker/__init__.py
lanyocr/benchmarker/benchmarker_icdar2015.py
lanyocr/benchmarker/detector_utils.py
lanyocr/benchmarker/ocr_utils.py
lanyocr/text_detector/__init__.py
lanyocr/text_detector/easyocr_craft.py
lanyocr/text_detector/paddleocr_en_ppocrv3.py
lanyocr/text_detector/paddleocr_en_ppocrv3_fp16.py
lanyocr/text_merger/__init__.py
lanyocr/text_merger/lanyocr_craft_merger.py
lanyocr/text_merger/lanyocr_nomerger.py
lanyocr/text_recognizer/__init__.py
lanyocr/text_recognizer/mmocr.py
lanyocr/text_recognizer/mmocr_satrn.py
lanyocr/text_recognizer/mmocr_satrn_sm.py
lanyocr/text_recognizer/paddleocr_base.py
lanyocr/text_recognizer/paddleocr_ch_ppocr_server_v2.py
lanyocr/text_recognizer/paddleocr_en_number_mobile_v2.py
lanyocr/text_recognizer/paddleocr_en_ppocrv3.py
lanyocr/text_recognizer/paddleocr_en_ppocrv3_fp16.py
lanyocr/text_recognizer/paddleocr_french_mobile_v2.py
lanyocr/text_recognizer/paddleocr_latin_mobile_v2.py
lanyocr/text_recognizer/dicts/__init__.py
lanyocr/text_recognizer/dicts/paddleocr_en_dict.json
lanyocr/text_recognizer/dicts/paddleocr_french_dict.json
lanyocr/text_recognizer/dicts/paddleocr_latin_dict.json
lanyocr/text_recognizer/dicts/ppocr_keys_v1_mod.json
lanyocr-0.1.12.data/data/lanyocr/text_recognizer/dicts/paddleocr_en_dict.json
lanyocr-0.1.12.data/data/lanyocr/text_recognizer/dicts/paddleocr_french_dict.json
lanyocr-0.1.12.data/data/lanyocr/text_recognizer/dicts/paddleocr_latin_dict.json
lanyocr-0.1.12.data/data/lanyocr/text_recognizer/dicts/ppocr_keys_v1_mod.json
lanyocr-0.1.12.dist-info/LICENSE
lanyocr-0.1.12.dist-info/METADATA
lanyocr-0.1.12.dist-info/WHEEL
lanyocr-0.1.12.dist-info/top_level.txt
lanyocr-0.1.12.dist-info/RECORD
