Metadata-Version: 2.1
Name: lanyocr
Version: 0.1.12
Summary: An OCR library for Python
Home-page: https://github.com/JC1DA/lanyocr
Download-URL: https://github.com/JC1DA/lanyocr
Author: JC1DA
Author-email: jc1da.3011@gmail.com
License: MIT
Keywords: ocr
Platform: UNKNOWN
Classifier: Development Status :: 3 - Alpha
Classifier: Intended Audience :: Developers
Classifier: Topic :: Software Development :: Build Tools
Classifier: License :: OSI Approved :: MIT License
Classifier: Programming Language :: Python :: 3.6
Requires-Python: >=3.0
License-File: LICENSE
Requires-Dist: onnxruntime-gpu (<1.14)
Requires-Dist: numpy (>=1.21)
Requires-Dist: opencv-python (>=4.5)
Requires-Dist: pydantic (>=1.10)
Requires-Dist: shapely
Requires-Dist: pyclipper
Requires-Dist: requests
